LICENSE.txt
README.md
setup.py
UERUS/UERUS.py
UERUS.egg-info/PKG-INFO
UERUS.egg-info/SOURCES.txt
UERUS.egg-info/dependency_links.txt
UERUS.egg-info/requires.txt
UERUS.egg-info/top_level.txt